texplain/__init__.py
texplain/_version.py
texplain-0.8.11.dist-info/LICENSE
texplain-0.8.11.dist-info/METADATA
texplain-0.8.11.dist-info/WHEEL
texplain-0.8.11.dist-info/entry_points.txt
texplain-0.8.11.dist-info/top_level.txt
texplain-0.8.11.dist-info/RECORD
