Metadata-Version: 2.1
Name: texplain
Version: 0.8.11
Summary: TeX file formatting
Author-email: Tom de Geus <tom@geus.me>
Project-URL: Source, https://github.com/tdegeus/texplain
Classifier: License :: OSI Approved :: MIT License
Requires-Python: >=3.6
License-File: LICENSE
Requires-Dist: numpy
Requires-Dist: click
